genericopenauth/__init__.py
genericopenauth/genericopenauth.py
genericopenauth-1.0.0.dist-info/METADATA
genericopenauth-1.0.0.dist-info/WHEEL
genericopenauth-1.0.0.dist-info/top_level.txt
genericopenauth-1.0.0.dist-info/RECORD
